configutator/__init__.py
configutator/__version.py
configutator/extraTypes.py
configutator/tui.py
configutator/util.py
configutator/valitator.py
configutator-1.0.2.dist-info/DESCRIPTION.rst
configutator-1.0.2.dist-info/METADATA
configutator-1.0.2.dist-info/RECORD
configutator-1.0.2.dist-info/WHEEL
configutator-1.0.2.dist-info/metadata.json
configutator-1.0.2.dist-info/top_level.txt
