Metadata-Version: 2.0
Name: configutator
Version: 1.0.2
Summary: Maps yaml nodes and command line arguments to python function parameters.
Home-page: https://github.com/innovate-invent/configutator
Author: Nolan
Author-email: innovate.invent@gmail.com
License: MIT
Platform: UNKNOWN
Requires-Dist: ruamel.yaml
Requires-Dist: jmespath
Requires-Dist: asciimatics
